yokoten/config.yaml.default
yokoten/main.py
yokoten/template/report.html
yokoten-0.1.1.dist-info/licenses/LICENSE
yokoten-0.1.1.dist-info/METADATA
yokoten-0.1.1.dist-info/WHEEL
yokoten-0.1.1.dist-info/entry_points.txt
yokoten-0.1.1.dist-info/top_level.txt
yokoten-0.1.1.dist-info/RECORD
