Metadata-Version: 2.4
Name: yokoten
Version: 0.1.1
Summary: Yokotenkai tool
Author-email: sasanquaneuf <sasanquaneuf@gmail.com>
Keywords: llm,refactoring,grep,automation
Classifier: License :: OSI Approved :: MIT License
Classifier: Programming Language :: Python :: 3 :: Only
Classifier: Programming Language :: Python :: 3.9
Classifier: Programming Language :: Python :: 3.10
Classifier: Programming Language :: Python :: 3.11
Classifier: Intended Audience :: Developers
Classifier: Topic :: Software Development :: Version Control :: Git
Requires-Python: >=3.9
License-File: LICENSE
Requires-Dist: PyYAML
Requires-Dist: google-generativeai
Requires-Dist: vertexai
Requires-Dist: boto3
Requires-Dist: openai
Dynamic: license-file
